{"name":"Success search job by city and title","id":"job-search;success-search-job-by-city-and-title","testSteps":[{"number":1,"description":"Given I go to button job search","duration":2,"startTime":"2022-10-06T15:40:51.864168+07:00[Asia/Jakarta]","result":"SUCCESS","precondition":false,"level":0},{"number":2,"description":"When I input job title and job city of job","duration":2,"startTime":"2022-10-06T15:40:51.868167200+07:00[Asia/Jakarta]","result":"SUCCESS","precondition":false,"level":0},{"number":3,"description":"And tab enter","duration":2,"startTime":"2022-10-06T15:40:51.871165400+07:00[Asia/Jakarta]","result":"SUCCESS","precondition":false,"level":0},{"number":4,"description":"Then I can see the list of job based on job city and job title that i want","duration":1,"startTime":"2022-10-06T15:40:51.874168+07:00[Asia/Jakarta]","result":"SUCCESS","precondition":false,"level":0}],"userStory":{"id":"job-search","storyName":"Job Search","displayName":"Job Search","path":"job/jobSearch.feature","narrative":"  As a user\n  I want to find a job\n  so that i can get the detail of job","type":"feature"},"featureTag":{"name":"Job/Job Search","type":"feature","displayName":"Job/Job Search"},"title":"Success search job by city and title","description":"","tags":[{"name":"Job","type":"capability","displayName":"Job"},{"name":"Job/Job Search","type":"feature","displayName":"Job Search"}],"startTime":"2022-10-06T15:40:51.858168800+07:00[Asia/Jakarta]","duration":18,"projectKey":"","isManualTestingUpToDate":false,"manual":false,"testSource":"Cucumber","result":"SUCCESS"}